udotcolors/__init__.py
udotcolors/_version.py
udotcolors/colors.py
udotcolors/palettes.py
udotcolors/plotnine/__init__.py
udotcolors/plotnine/palettes.py
udotcolors/plotnine/scales.py
udotcolors/seaborn/__init__.py
udotcolors/seaborn/palettes.py
udotcolors-0.1.2.dist-info/LICENSE
udotcolors-0.1.2.dist-info/METADATA
udotcolors-0.1.2.dist-info/WHEEL
udotcolors-0.1.2.dist-info/top_level.txt
udotcolors-0.1.2.dist-info/RECORD
