Metadata-Version: 2.1
Name: udotcolors
Version: 0.1.2
Summary: Colors and palettes for varios Python plotting packages that conform to the UDOT style guide
Author-email: Hayden Atchley <hatchley@utah.gov>
Project-URL: Homepage, https://github.com/atchley-sha/udot-colors-seaborn
Project-URL: Issues, https://github.com/atchley-sha/udot-colors-seaborn/issues
Classifier: Programming Language :: Python :: 3
Classifier: License :: OSI Approved :: MIT License
Classifier: Operating System :: OS Independent
Requires-Python: >=3.9
License-File: LICENSE
Provides-Extra: plotnine
Requires-Dist: plotnine; extra == "plotnine"
Provides-Extra: seaborn
Requires-Dist: ColorKit; extra == "seaborn"
Requires-Dist: seaborn; extra == "seaborn"
